Flask_Vue-0.3.4.dist-info/DESCRIPTION.rst
Flask_Vue-0.3.4.dist-info/METADATA
Flask_Vue-0.3.4.dist-info/RECORD
Flask_Vue-0.3.4.dist-info/WHEEL
Flask_Vue-0.3.4.dist-info/metadata.json
Flask_Vue-0.3.4.dist-info/top_level.txt
flask_vue/__init__.py
flask_vue/cdn.py
flask_vue/config.py
flask_vue/static/vue-async-data.js
flask_vue/static/vue-async-data.min.js
flask_vue/static/vue-form.js
flask_vue/static/vue-form.min.js
flask_vue/static/vue-i18n.js
flask_vue/static/vue-i18n.min.js
flask_vue/static/vue-resource.js
flask_vue/static/vue-resource.min.js
flask_vue/static/vue-router.js
flask_vue/static/vue-router.min.js
flask_vue/static/vue-strap.js
flask_vue/static/vue-strap.min.js
flask_vue/static/vue-table.js
flask_vue/static/vue-table.min.js
flask_vue/static/vue-validator.js
flask_vue/static/vue-validator.min.js
flask_vue/static/vue.js
flask_vue/static/vue.min.js
flask_vue/static/vuex.js
flask_vue/static/vuex.min.js
flask_vue/templates/vue/base.html
