Metadata-Version: 2.0
Name: Flask-Vue
Version: 0.3.4
Summary: Vue.js 1.0+ integration for Flask (Python 3 version)
Home-page: https://github.com/taogeT/flask-vue
Author: Zheng Wentao
Author-email: zwtzjd@gmail.com
License: Apache
Platform: any
Classifier: Development Status :: 4 - Beta
Classifier: Environment :: Web Environment
Classifier: Framework :: Flask
Classifier: Intended Audience :: Developers
Classifier: License :: OSI Approved :: Apache Software License
Classifier: Operating System :: OS Independent
Classifier: Programming Language :: Python
Classifier: Programming Language :: Python :: 3
Classifier: Programming Language :: Python :: 3.4
Classifier: Programming Language :: Python :: 3.5
Classifier: Programming Language :: Python :: 3.6
Classifier: Topic :: Internet :: WWW/HTTP :: Dynamic Content
Classifier: Topic :: Software Development :: Libraries :: Python Modules
Requires-Dist: Flask (>=0.11)
